[
  {
    "nome": "Revolta de Males",
    "data": "24 de jan. de 1835 – 25 de jan. de 1835",
    "canvas": "/contexto"
  },
  {
    "nome": "Revolta de Cabanagem",
    "data": "24 de jan. de 1835 – 25 de jan. de 1835",
    "canvas": "/diferenca"
  },
  {
    "nome": "Revolta de AAA",
    "data": "24 de jan. de 1835 – 25 de jan. de 1835",
    "canvas": "https://www.geoguessr.com/"
  },
  {
    "nome": "Revolta de Cabanagem",
    "data": "24 de jan. de 1835 – 25 de jan. de 1835",
    "canvas": ""
  },
  {
    "nome": "Revolta de Cabanagem",
    "data": "24 de jan. de 1835 – 25 de jan. de 1835",
    "canvas": ""
  },
  {
    "nome": "Revolta de Cabanagem",
    "data": "24 de jan. de 1835 – 25 de jan. de 1835",
    "canvas": ""
  },
  {
    "nome": "Revolta de Cabanagem",
    "data": "24 de jan. de 1835 – 25 de jan. de 1835",
    "canvas": ""
  },
  {
    "nome": "Revolta de Cabanagem",
    "data": "24 de jan. de 1835 – 25 de jan. de 1835",
    "canvas": ""
  }
]
